{
    "id": 2714743,
    "name": "for th3name",
    "author": "cache",
    "creators": ["cache"],
    "verifier": "cache",
    "verification": "https://youtube.com/watch?v=5gtgaQREpmQ",
    "percentToQualify": 100,
    "records": [
        {
            "user": "sixfevers/fwogreal",
            "link": "https://youtu.be/gyqjLQ4wA3M",
            "percent": 100,
            "hz": 60

        },
        {
            "user": "okman241",
            "link": "https://www.youtube.com/watch?v=IC95R4oGCoc",
            "percent": 100,
            "hz": 240
        }
    ]
}